[
    {"QuarterId":661710,"Name":"KAMIŞ","TypeCode":4,"TypeDescription":"SOKAK","Id":36473,"LastUpdate":null},
    {"QuarterId":668822,"Name":"CEVİZLİK MEVKİİ","TypeCode":5,"TypeDescription":"KÜME EVLERİ","Id":79086,"LastUpdate":null},
    {"QuarterId":668822,"Name":"TIRANKO MEVKİİ","TypeCode":5,"TypeDescription":"KÜME EVLERİ","Id":80973,"LastUpdate":null},
    {"QuarterId":661710,"Name":"İNCİR","TypeCode":4,"TypeDescription":"SOKAK","Id":86064,"LastUpdate":null},
    {"QuarterId":661710,"Name":"BADEM","TypeCode":4,"TypeDescription":"SOKAK","Id":86074,"LastUpdate":null},
    {"QuarterId":661710,"Name":"BEGONYA","TypeCode":4,"TypeDescription":"SOKAK","Id":86077,"LastUpdate":null},
    {"QuarterId":661710,"Name":"SAZAK","TypeCode":4,"TypeDescription":"SOKAK","Id":132432,"LastUpdate":null},
    {"QuarterId":668822,"Name":"DOKTOR EVLERİ MEVKİİ","TypeCode":5,"TypeDescription":"KÜME EVLERİ","Id":136520,"LastUpdate":null},
    {"QuarterId":668822,"Name":"ÇALOĞLU MEVKİİ","TypeCode":5,"TypeDescription":"KÜME EVLERİ","Id":156215,"LastUpdate":null},
    {"QuarterId":661710,"Name":"KARANFİL","TypeCode":4,"TypeDescription":"SOKAK","Id":326894,"LastUpdate":null},
    {"QuarterId":668319,"Name":"ÇAY","TypeCode":5,"TypeDescription":"KÜME EVLERİ","Id":482243,"LastUpdate":null},
    {"QuarterId":661710,"Name":"KASIMPATI","TypeCode":4,"TypeDescription":"SOKAK","Id":523546,"LastUpdate":null},
    {"QuarterId":661710,"Name":"ŞEYH ŞAMİL","TypeCode":4,"TypeDescription":"SOKAK","Id":523571,"LastUpdate":null},
    {"QuarterId":661710,"Name":"KEKİK","TypeCode":4,"TypeDescription":"SOKAK","Id":523578,"LastUpdate":null},
    {"QuarterId":661710,"Name":"SEBİL","TypeCode":4,"TypeDescription":"SOKAK","Id":523588,"LastUpdate":null},
    {"QuarterId":661710,"Name":"KAMELYA","TypeCode":4,"TypeDescription":"SOKAK","Id":523625,"LastUpdate":null},
    {"QuarterId":661710,"Name":"BALLIBABA","TypeCode":4,"TypeDescription":"SOKAK","Id":523890,"LastUpdate":null},
    {"QuarterId":661710,"Name":"AHUDUDU","TypeCode":4,"TypeDescription":"SOKAK","Id":524085,"LastUpdate":null},
    {"QuarterId":661710,"Name":"SAFA","TypeCode":4,"TypeDescription":"SOKAK","Id":524572,"LastUpdate":null},
    {"QuarterId":661710,"Name":"CEVİZ","TypeCode":4,"TypeDescription":"SOKAK","Id":524761,"LastUpdate":null},
    {"QuarterId":661710,"Name":"KESTANE","TypeCode":4,"TypeDescription":"SOKAK","Id":524765,"LastUpdate":null},
    {"QuarterId":661710,"Name":"KİRAZ","TypeCode":4,"TypeDescription":"SOKAK","Id":525281,"LastUpdate":null},
    {"QuarterId":661710,"Name":"IHLAMUR","TypeCode":4,"TypeDescription":"SOKAK","Id":527040,"LastUpdate":null},
    {"QuarterId":661710,"Name":"KIRLANGIÇ","TypeCode":4,"TypeDescription":"SOKAK","Id":527042,"LastUpdate":null},
    {"QuarterId":661710,"Name":"SARAY","TypeCode":4,"TypeDescription":"SOKAK","Id":528829,"LastUpdate":null},
    {"QuarterId":661710,"Name":"HAVUÇ","TypeCode":4,"TypeDescription":"SOKAK","Id":531070,"LastUpdate":null},
    {"QuarterId":661710,"Name":"KOZA","TypeCode":4,"TypeDescription":"SOKAK","Id":531074,"LastUpdate":null},
    {"QuarterId":661710,"Name":"KARADUT","TypeCode":4,"TypeDescription":"SOKAK","Id":531167,"LastUpdate":null},
    {"QuarterId":661710,"Name":"ŞEHRAZAT","TypeCode":4,"TypeDescription":"SOKAK","Id":531169,"LastUpdate":null},
    {"QuarterId":661710,"Name":"RAHMET","TypeCode":4,"TypeDescription":"SOKAK","Id":531508,"LastUpdate":null},
    {"QuarterId":661710,"Name":"UMUT","TypeCode":4,"TypeDescription":"SOKAK","Id":531611,"LastUpdate":null},
    {"QuarterId":661710,"Name":"ILGIN","TypeCode":4,"TypeDescription":"SOKAK","Id":531612,"LastUpdate":null},
    {"QuarterId":661710,"Name":"GÜLİSTANLIK","TypeCode":4,"TypeDescription":"SOKAK","Id":531613,"LastUpdate":null},
    {"QuarterId":661710,"Name":"AKASYA","TypeCode":4,"TypeDescription":"SOKAK","Id":531677,"LastUpdate":null},
    {"QuarterId":661710,"Name":"ARDIÇ","TypeCode":4,"TypeDescription":"SOKAK","Id":531953,"LastUpdate":null},
    {"QuarterId":661710,"Name":"KAVAK","TypeCode":4,"TypeDescription":"SOKAK","Id":531958,"LastUpdate":null},
    {"QuarterId":661710,"Name":"GÜNDOĞDU","TypeCode":4,"TypeDescription":"SOKAK","Id":531959,"LastUpdate":null},
    {"QuarterId":661710,"Name":"OSMANGAZİ","TypeCode":4,"TypeDescription":"SOKAK","Id":532448,"LastUpdate":null},
    {"QuarterId":661710,"Name":"ALTINBAŞ","TypeCode":4,"TypeDescription":"SOKAK","Id":534157,"LastUpdate":null},
    {"QuarterId":661710,"Name":"KALEM","TypeCode":4,"TypeDescription":"SOKAK","Id":534158,"LastUpdate":null},
    {"QuarterId":661710,"Name":"ORHANGAZİ","TypeCode":4,"TypeDescription":"SOKAK","Id":534666,"LastUpdate":null},
    {"QuarterId":661710,"Name":"YENİDÜNYA","TypeCode":4,"TypeDescription":"SOKAK","Id":534667,"LastUpdate":null},
    {"QuarterId":661710,"Name":"UFUK","TypeCode":4,"TypeDescription":"SOKAK","Id":535859,"LastUpdate":null},
    {"QuarterId":661710,"Name":"ÇAĞLA","TypeCode":4,"TypeDescription":"SOKAK","Id":535943,"LastUpdate":null},
    {"QuarterId":661710,"Name":"İRFAN","TypeCode":4,"TypeDescription":"SOKAK","Id":535946,"LastUpdate":null},
    {"QuarterId":661710,"Name":"KARDELEN","TypeCode":4,"TypeDescription":"SOKAK","Id":543256,"LastUpdate":null},
    {"QuarterId":661710,"Name":"KARTOPU","TypeCode":4,"TypeDescription":"SOKAK","Id":543258,"LastUpdate":null},
    {"QuarterId":661710,"Name":"SEVGİ","TypeCode":4,"TypeDescription":"SOKAK","Id":545092,"LastUpdate":null},
    {"QuarterId":668822,"Name":"KETENCİLER AŞAĞI MEVKİİ","TypeCode":5,"TypeDescription":"KÜME EVLERİ","Id":715279,"LastUpdate":null},
    {"QuarterId":668822,"Name":"KETENCİLER ORTA MEVKİİ","TypeCode":5,"TypeDescription":"KÜME EVLERİ","Id":718041,"LastUpdate":null},
    {"QuarterId":668822,"Name":"CAMİ MEVKİİ","TypeCode":5,"TypeDescription":"KÜME EVLERİ","Id":720148,"LastUpdate":null},
    {"QuarterId":668822,"Name":"YUKARI MEVKİİ","TypeCode":5,"TypeDescription":"KÜME EVLERİ","Id":720406,"LastUpdate":null},
    {"QuarterId":668822,"Name":"AKMEŞE YOLU MEVKİİ","TypeCode":5,"TypeDescription":"KÜME EVLERİ","Id":720752,"LastUpdate":null},
    {"QuarterId":668822,"Name":"GİRESUNLULAR MEVKİİ","TypeCode":5,"TypeDescription":"KÜME EVLERİ","Id":723989,"LastUpdate":null},
    {"QuarterId":668822,"Name":"KARAAĞAÇ MEVKİİ","TypeCode":5,"TypeDescription":"KÜME EVLERİ","Id":724108,"LastUpdate":null},
    {"QuarterId":668822,"Name":"İBRİKDERE YOLU MEVKİİ","TypeCode":5,"TypeDescription":"KÜME EVLERİ","Id":725287,"LastUpdate":null},
    {"QuarterId":661710,"Name":"CEYLAN","TypeCode":4,"TypeDescription":"SOKAK","Id":878115,"LastUpdate":null},
    {"QuarterId":661710,"Name":"VURANKAYA","TypeCode":4,"TypeDescription":"SOKAK","Id":888285,"LastUpdate":null},
    {"QuarterId":661710,"Name":"ALPEREN","TypeCode":4,"TypeDescription":"SOKAK","Id":892192,"LastUpdate":null},
    {"QuarterId":661710,"Name":"AYÇİÇEĞİ","TypeCode":4,"TypeDescription":"SOKAK","Id":892922,"LastUpdate":null},
    {"QuarterId":668319,"Name":"ŞEHİT ASTSUBAY ÖMER HALİSDEMİR - YAZIKÖY","TypeCode":3,"TypeDescription":"CADDESİ","Id":953932,"LastUpdate":null},
    {"QuarterId":668319,"Name":"ŞEHİT ASTSUBAY ÖMER HALİSDEMİR - YAZIKÖY","TypeCode":3,"TypeDescription":"CADDESİ","Id":953934,"LastUpdate":null},
    {"QuarterId":661710,"Name":"VİŞNE","TypeCode":4,"TypeDescription":"SOKAK","Id":1080133,"LastUpdate":null},
    {"QuarterId":668822,"Name":"234.","TypeCode":4,"TypeDescription":"SOKAK","Id":65396483,"LastUpdate":null},
    {"QuarterId":661710,"Name":"AKMEŞE","TypeCode":4,"TypeDescription":"SOKAK","Id":312944570,"LastUpdate":null},
    {"QuarterId":668319,"Name":"AŞAĞI","TypeCode":5,"TypeDescription":"KÜME EVLERİ","Id":428342670,"LastUpdate":null},
    {"QuarterId":661710,"Name":"ULUPINAR","TypeCode":3,"TypeDescription":"CADDESİ","Id":731420771,"LastUpdate":null},
    {"QuarterId":661710,"Name":"AFYON","TypeCode":3,"TypeDescription":"CADDESİ","Id":770225490,"LastUpdate":null},
    {"QuarterId":661710,"Name":"ÜZÜM","TypeCode":4,"TypeDescription":"SOKAK","Id":943696910,"LastUpdate":null}
]